drive_utils/__init__.py
drive_utils/google_utils.py
drive_utils-1.0.0.dist-info/WHEEL
drive_utils-1.0.0.dist-info/METADATA
drive_utils-1.0.0.dist-info/RECORD
