Metadata-Version: 2.1
Name: drive-utils
Version: 1.0.0
Summary: Useful functions of Google Drive API for python
Home-page: https://github.com/loft-br/finance-drive-utils
Author: LucasCiziks
Author-email: lucas.ciziks@loft.com.br
Requires-Python: >=3.7,<4.0
Classifier: Programming Language :: Python :: 3
Classifier: Programming Language :: Python :: 3.7
Classifier: Programming Language :: Python :: 3.8
Classifier: Programming Language :: Python :: 3.9
Requires-Dist: google-api-python-client (==2.4.0)
Requires-Dist: oauth2client (==4.1.3)
Requires-Dist: pandas (==1.3.3)
Project-URL: Repository, https://github.com/loft-br/finance-drive-utils
